milcatrusspy/__init__.py
milcatrusspy/analasis.py
milcatrusspy/model.py
milcatrusspy/node.py
milcatrusspy/truss_element.py
milcatrusspy-0.1.1.dist-info/METADATA
milcatrusspy-0.1.1.dist-info/WHEEL
milcatrusspy-0.1.1.dist-info/top_level.txt
milcatrusspy-0.1.1.dist-info/RECORD
