Metadata-Version: 2.4
Name: milcatrusspy
Version: 0.1.1
Summary: Librería para el análisis de estructuras (Truss).
Home-page: https://github.com/Milca-py/milcatrusspy
Author: Amilcar
Author-email: 200190@unsaac.edu.pe
Requires-Dist: numpy
Requires-Dist: pandas
Requires-Dist: matplotlib
Dynamic: author
Dynamic: author-email
Dynamic: description
Dynamic: description-content-type
Dynamic: home-page
Dynamic: requires-dist
Dynamic: summary
